nardini/__init__.py
nardini/__main__.py
nardini/constants.py
nardini/core.py
nardini/plotting.py
nardini/score_and_plot.py
nardini/utils.py
nardini/validation.py
nardini-1.1.1.dist-info/LICENSE
nardini-1.1.1.dist-info/METADATA
nardini-1.1.1.dist-info/WHEEL
nardini-1.1.1.dist-info/entry_points.txt
nardini-1.1.1.dist-info/top_level.txt
nardini-1.1.1.dist-info/RECORD
