Metadata-Version: 2.1
Name: nardini
Version: 1.1.1
Summary: Nardini is a Python package for IDP sequences that generates similar sequences derived from a statistical analysis of residue-specific asymmetries across short blob sizes, calculated across bootstrapped sequences.
Author-email: Min Kyung Shinn <mshinn@wustl.edu>, Megan Cohan <mcohan@wustl.edu>, Kiersten Ruff <kiersten.ruff@wustl.edu>
Maintainer-email: Jared Lalmansingh <jared.lalmansingh@wustl.edu>
License: GNU GENERAL PUBLIC LICENSE
Project-URL: homepage, https://github.com/mshinn23/nardini
Project-URL: repository, https://github.com/mshinn23/nardini.git
Project-URL: issues, https://github.com/mshinn23/nardini/issues
Keywords: bioinformatics,sequence analysis,intrinsically disordered proteins,IDPs,z-score
Classifier: Natural Language :: English
Classifier: Intended Audience :: Developers
Classifier: Intended Audience :: Science/Research
Classifier: Topic :: Scientific/Engineering :: Bio-Informatics
Classifier: Operating System :: OS Independent
Classifier: License :: OSI Approved :: GNU General Public License v3 or later (GPLv3+)
Classifier: Programming Language :: Python :: 3.5
Classifier: Programming Language :: Python :: 3.6
Classifier: Programming Language :: Python :: 3.7
Classifier: Programming Language :: Python :: 3.8
Classifier: Programming Language :: Python :: 3.9
Classifier: Programming Language :: Python :: 3.10
Classifier: Programming Language :: Python :: 3.11
Requires-Python: >=3.5
License-File: LICENSE
Requires-Dist: BioPython (>=1.75)
Requires-Dist: matplotlib (>=3.3)
Requires-Dist: numpy (>=1.19)
Requires-Dist: scipy (<1.7)
Requires-Dist: pandas (>=1.2)
Requires-Dist: tabulate (>=0.8)
